{
    "MetaData": {
        "ContentFormatVersion": 4,
        "Id": "NightmareBotMonkeyKingBuff",
        "Name": "NightmareBotMonkeyKingBuff",
        "ResourcePath": "DATA/Spells/NightmareBotMonkeyKingBuff.inibin"
    },
    "Values": {
        "BuffData": {
            "DynamicTooltip": "<titleLeft>Doom Wukong</titleLeft><mainText>Doom Wukong’s Nimbus Strike creates additional clones which knock enemies into the air when disappearing. His Cyclone also summons Decoys that spin alongside him.</mainText><postScriptLeft>Source: @SourceName@</postScriptLeft>"
        }
    }
}