{
    "MetaData": {
        "ContentFormatVersion": 4,
        "Id": "TreelineMasterBuffT0",
        "Name": "TreelineMasterBuffT0",
        "ResourcePath": "DATA/Spells/TreelineMasterBuffT0.inibin"
    },
    "Values": {
        "BuffData": {
            "DynamicTooltip": "<titleLeft>No Altars</titleLeft><mainText>Capture Altars to increase your power!<br><br><font color='#FF9900'>0 Altars Controlled</font><br> +Bonus Mana Regeneration<br><font color='#505050'> +3 Gold per Kill<br> +10% Bonus Attack Damage<br> +10% Ability Power</font></mainText><postScriptLeft>Source: @SourceName@</postScriptLeft>"
        }
    }
}