{
    "MetaData": {
        "ContentFormatVersion": 4,
        "Id": "TreelineMasterBuffT1RightHexakill",
        "Name": "TreelineMasterBuffT1RightHexakill",
        "ResourcePath": "DATA/Spells/TreelineMasterBuffT1RightHexakill.inibin"
    },
    "Values": {
        "BuffData": {
            "DynamicTooltip": "<titleLeft>One Altar (Hexakill)</titleLeft><mainText>Capture Altars to increase your power!<br><br><font color='#FF9900'>1 Altar Controlled</font><br> +Bonus Mana Regeneration<br> Minions spawn with +@f1@% Health and Damage<br><font color='#505050'> +10% Bonus Attack Damage<br> +10% Ability Power</font></mainText><postScriptLeft>Source: @SourceName@</postScriptLeft>"
        }
    }
}