{
    "MetaData": {
        "ContentFormatVersion": 4,
        "Id": "NightmareBotSpiritShaco",
        "Name": "NightmareBotSpiritShaco",
        "ResourcePath": "DATA/Spells/NightmareBotSpiritShaco.inibin"
    },
    "Values": {
        "BuffData": {
            "DynamicTooltip": "<titleLeft>Bonus Doom: Hallucinate</titleLeft><mainText>Whenever this champion is below 40% health, they create a clone of themselves, which explodes when dying dealing magic damage to nearby enemies.</mainText><postScriptLeft>Source: @SourceName@</postScriptLeft>"
        }
    }
}