{
    "MetaData": {
        "ContentFormatVersion": 4,
        "Id": "XerathLocusOfPower2",
        "Name": "Rite of the Arcane",
        "ResourcePath": "DATA/Characters/Xerath/Spells/XerathLocusOfPower2.inibin"
    },
    "Values": {
        "SpellData": {
            "AnimationName": "Spell5Start",
            "CantCancelWhileChanneling": 0,
            "CantCancelWhileWindingUp": 1,
            "CastFrame": 7.5,
            "CastRange": 3200,
            "CastRange1": 3200,
            "CastRange2": 4400,
            "CastRange3": 5600,
            "CastType": 0,
            "ChannelDuration": 10,
            "Coefficient": 0.43,
            "Cooldown": 130.0,
            "Cooldown1": 130.0,
            "Cooldown2": 115.0,
            "Cooldown3": 100.0,
            "Description": "Xerath immobilizes himself and gains three shots of a long-range attack.",
            "DisplayName": "Rite of the Arcane",
            "DynamicExtended": "<postScriptTitle>Next Level - click to level-up or press [@LevelUpHotkey@].</postScriptTitle><postScriptLeft>Damage<br>Range<br>Cooldown</postScriptLeft><postScriptRight>@Effect3Amount@ -> @Effect3AmountNL@<br>@Effect5Amount@ -> @Effect5AmountNL@<br>@Cooldown@ -> @CooldownNL@</postScriptRight>",
            "DynamicTooltip": "<titleLeft>Rite of the Arcane (@Level@)</titleLeft><titleRight>[@Hotkey@]</titleRight><subtitleLeft>@Cost@ Mana</subtitleLeft><subtitleRight>@Cooldown@ sec Cooldown</subtitleRight><mainText>Xerath ascends to his true form, becoming rooted in place and gaining @Effect2Amount@ Arcane Barrages. This magic artillery deals @Effect3Amount@ <font color='#99FF99'>(+@CharAbilityPower@)</font> magic damage to all enemies hit.<br><br>The root ends after @Effect1Amount@ seconds, when all shots have been fired or when manually deactivated by issuing a move command. If Xerath does not fire off a single Arcane Barrage, half of the cooldown of Rite of the Arcane is refunded.</mainText>",
            "Effect1Level0Amount": 10,
            "Effect1Level1Amount": 10,
            "Effect1Level2Amount": 10,
            "Effect1Level3Amount": 10,
            "Effect2Level0Amount": 3,
            "Effect2Level1Amount": 3,
            "Effect2Level2Amount": 3,
            "Effect2Level3Amount": 3,
            "Effect3Level0Amount": 190,
            "Effect3Level1Amount": 190,
            "Effect3Level2Amount": 245,
            "Effect3Level3Amount": 300,
            "Effect4Level0Amount": 190,
            "Effect4Level1Amount": 190,
            "Effect4Level2Amount": 190,
            "Effect4Level3Amount": 190,
            "Effect5Level0Amount": 3200,
            "Effect5Level1Amount": 3200,
            "Effect5Level2Amount": 4400,
            "Effect5Level3Amount": 5600,
            "Flags": 262144,
            "InventoryIcon": "Xerath_R1.dds",
            "ManaCost1": 100.0,
            "ManaCost2": 100.0,
            "ManaCost3": 100.0,
            "OverrideCastTime": 0.5,
            "TargettingType": 4,
            "UseAnimatorFramerate": 1,
            "UseMinimapTargeting": 1
        }
    }
}